mycroft_plugin_tts_mimic3
